record_list-0.2.3.dist-info/licenses/LICENSE
rlist/__init__.py
rlist/rlist.py
rlist/types.py
record_list-0.2.3.dist-info/METADATA
record_list-0.2.3.dist-info/WHEEL
record_list-0.2.3.dist-info/top_level.txt
record_list-0.2.3.dist-info/RECORD
