Metadata-Version: 2.4
Name: record-list
Version: 0.2.3
Summary: Record list with handy methods
Author-email: Maximos Nikiforakis <nikiforos@live.co.uk>
License-Expression: MIT
Project-URL: Documentation, https://maxcode123.github.io/rlist/
Project-URL: Repository, https://github.com/Maxcode123/rlist
Project-URL: Issues, https://github.com/Maxcode123/rlist/issues
Keywords: rlist,list
Requires-Python: >=3.10
License-File: LICENSE
Dynamic: license-file
